eng/__init__.py
eng/generate_code.py
eng/templates/app.template
eng/templates/service.template
eng/templates/view.template
engel/__init__.py
engel/application.py
engel/engeljs.js
engel/index.html
engel/utils.py
engel/websocket.py
engel/libraries/__init__.py
engel/libraries/bootstrap4/__init__.py
engel/libraries/bootstrap4/widgets/__init__.py
engel/libraries/bootstrap4/widgets/structure.py
engel/widgets/__init__.py
engel/widgets/abstract.py
engel/widgets/base.py
engel/widgets/forms.py
engel/widgets/media.py
engel/widgets/structure.py
engel/widgets/text.py
engel-0.3.1.dist-info/DESCRIPTION.rst
engel-0.3.1.dist-info/entry_points.txt
engel-0.3.1.dist-info/METADATA
engel-0.3.1.dist-info/metadata.json
engel-0.3.1.dist-info/RECORD
engel-0.3.1.dist-info/top_level.txt
engel-0.3.1.dist-info/WHEEL
