Metadata-Version: 2.0
Name: engel
Version: 0.3.1
Summary: Build rock-solid web interfaces for your projects.
Home-page: https://github.com/Dalloriam/engel
Author: Dalloriam
Author-email: dalloriam@gmail.com
License: MIT
Platform: UNKNOWN
Requires-Dist: autobahn (==0.13.0)
Requires-Dist: requests (==2.10.0)
Requires-Dist: asyncio (==3.4.3)
